cardioception/__init__.py
cardioception/reports.py
cardioception/stats.py
cardioception/HBC/__init__.py
cardioception/HBC/parameters.py
cardioception/HBC/task.py
cardioception/HBC/Images/__init__.py
cardioception/HBC/Images/heartbeat.png
cardioception/HBC/Images/rest.png
cardioception/HBC/Sounds/__init__.py
cardioception/HBC/Sounds/start.wav
cardioception/HBC/Sounds/stop.wav
cardioception/HRD/__init__.py
cardioception/HRD/generate_sound_stimuli.py
cardioception/HRD/languages.py
cardioception/HRD/parameters.py
cardioception/HRD/task.py
cardioception/HRD/Images/hand.png
cardioception/HRD/Images/hand.svg
cardioception/HRD/Images/heartbeat.png
cardioception/HRD/Images/listen.png
cardioception/HRD/Images/listenResponse.png
cardioception/HRD/Images/pulseOximeter.png
cardioception/HRD/Images/pulseOximeter.svg
cardioception/HRD/Sounds/100.0.wav
cardioception/HRD/Sounds/100.5.wav
cardioception/HRD/Sounds/101.0.wav
cardioception/HRD/Sounds/101.5.wav
cardioception/HRD/Sounds/102.0.wav
cardioception/HRD/Sounds/102.5.wav
cardioception/HRD/Sounds/103.0.wav
cardioception/HRD/Sounds/103.5.wav
cardioception/HRD/Sounds/104.0.wav
cardioception/HRD/Sounds/104.5.wav
cardioception/HRD/Sounds/105.0.wav
cardioception/HRD/Sounds/105.5.wav
cardioception/HRD/Sounds/106.0.wav
cardioception/HRD/Sounds/106.5.wav
cardioception/HRD/Sounds/107.0.wav
cardioception/HRD/Sounds/107.5.wav
cardioception/HRD/Sounds/108.0.wav
cardioception/HRD/Sounds/108.5.wav
cardioception/HRD/Sounds/109.0.wav
cardioception/HRD/Sounds/109.5.wav
cardioception/HRD/Sounds/110.0.wav
cardioception/HRD/Sounds/110.5.wav
cardioception/HRD/Sounds/111.0.wav
cardioception/HRD/Sounds/111.5.wav
cardioception/HRD/Sounds/112.0.wav
cardioception/HRD/Sounds/112.5.wav
cardioception/HRD/Sounds/113.0.wav
cardioception/HRD/Sounds/113.5.wav
cardioception/HRD/Sounds/114.0.wav
cardioception/HRD/Sounds/114.5.wav
cardioception/HRD/Sounds/115.0.wav
cardioception/HRD/Sounds/115.5.wav
cardioception/HRD/Sounds/116.0.wav
cardioception_toolbox-0.5.0.dist-info/LICENSE
cardioception_toolbox-0.5.0.dist-info/METADATA
cardioception_toolbox-0.5.0.dist-info/WHEEL
cardioception_toolbox-0.5.0.dist-info/top_level.txt
cardioception_toolbox-0.5.0.dist-info/RECORD
